pyarmorpacker/__init__.py
pyarmorpacker/build_meta.py
pyarmorpacker-1.5.dist-info/METADATA
pyarmorpacker-1.5.dist-info/WHEEL
pyarmorpacker-1.5.dist-info/top_level.txt
pyarmorpacker-1.5.dist-info/RECORD
