Metadata-Version: 2.1
Name: pyarmorpacker
Version: 1.5
Summary: UNKNOWN
Home-page: UNKNOWN
License: UNKNOWN
Platform: UNKNOWN
Requires-Dist: pyarmor (==7.2.3)
